zerocarbon/__init__.py
zerocarbon/client.py
zerocarbon/exceptions.py
zerocarbon_python_sdk-2.0.0.dist-info/METADATA
zerocarbon_python_sdk-2.0.0.dist-info/WHEEL
zerocarbon_python_sdk-2.0.0.dist-info/top_level.txt
zerocarbon_python_sdk-2.0.0.dist-info/RECORD
