Metadata-Version: 2.4
Name: zerocarbon-python-sdk
Version: 2.0.0
Summary: Official Python SDK for ZeroCarbon.codes API
Home-page: https://github.com/zerocarbon/python-sdk
Author: ZeroCarbon.codes
Author-email: "ZeroCarbon.codes" <support@zerocarbon.codes>
License: MIT
Project-URL: Homepage, https://zerocarbon.codes
Project-URL: Documentation, https://docs.zerocarbon.codes
Project-URL: Repository, https://github.com/zerocarbon/python-sdk
Keywords: carbon,emissions,climate,sustainability,offsetting,api
Classifier: Development Status :: 4 - Beta
Classifier: Intended Audience :: Developers
Classifier: License :: OSI Approved :: MIT License
Classifier: Programming Language :: Python :: 3
Classifier: Programming Language :: Python :: 3.8
Classifier: Programming Language :: Python :: 3.9
Classifier: Programming Language :: Python :: 3.10
Classifier: Programming Language :: Python :: 3.11
Requires-Python: >=3.8
Requires-Dist: requests>=2.28.0
Dynamic: author
Dynamic: home-page
Dynamic: requires-python
